current_time/__init__.py
current_time/server.py
e0_7_current_time_mcp-0.1.0.dist-info/METADATA
e0_7_current_time_mcp-0.1.0.dist-info/WHEEL
e0_7_current_time_mcp-0.1.0.dist-info/entry_points.txt
e0_7_current_time_mcp-0.1.0.dist-info/top_level.txt
e0_7_current_time_mcp-0.1.0.dist-info/RECORD
